etherscan/__init__.py
etherscan/errors.py
etherscan/etherscan.py
etherscan2-0.4.0.dist-info/LICENSE
etherscan2-0.4.0.dist-info/METADATA
etherscan2-0.4.0.dist-info/WHEEL
etherscan2-0.4.0.dist-info/top_level.txt
etherscan2-0.4.0.dist-info/RECORD
