Metadata-Version: 2.1
Name: etherscan2
Version: 0.4.0
Summary: Etherscan.io API wrapper
Home-page: https://github.com/gerrrg/etherscan
Author: @neoctobers
Author-email: neoctobers@gmail.com
License: UNKNOWN
Platform: UNKNOWN
Classifier: Programming Language :: Python :: 3
Classifier: License :: OSI Approved :: MIT License
Classifier: Operating System :: OS Independent
License-File: LICENSE
Requires-Dist: requests-cache
